Quant_AgentTools/__init__.py
Quant_AgentTools/agent_tools.py
Quant_AgentTools/prompts.py
Quant_AgentTools-0.3.1.dist-info/METADATA
Quant_AgentTools-0.3.1.dist-info/WHEEL
Quant_AgentTools-0.3.1.dist-info/top_level.txt
Quant_AgentTools-0.3.1.dist-info/RECORD
