Metadata-Version: 2.1
Name: Quant_AgentTools
Version: 0.3.1
Summary: Agentic Workflow with Quantized LLMs
Requires-Dist: pydantic
Requires-Dist: GPT4All
